csm_test_utils/__init__.py
csm_test_utils/__main__.py
csm_test_utils/common.py
csm_test_utils/continuous.py
csm_test_utils/continuous_entities.py
csm_test_utils/files_rotation.py
csm_test_utils/message.py
csm_test_utils/parsers.py
csm_test_utils/rebalance_test.py
csm_test_utils/autoscaling/__init__.py
csm_test_utils/autoscaling/loadbalancer.py
csm_test_utils/autoscaling/smn_webhook.py
csm_test_utils/dns/__init__.py
csm_test_utils/dns/dns_resolving.py
csm_test_utils/dns/host_check.py
csm_test_utils/loadbalancer/__init__.py
csm_test_utils/loadbalancer/lb_monitor.py
csm_test_utils/rds/__init__.py
csm_test_utils/rds/rds_backup.py
csm_test_utils/rds_backup/__init__.py
csm_test_utils/rds_backup/backup_check/__init__.py
csm_test_utils/rds_backup/backup_check/rds_backup.py
csm_test_utils/rds_backup/generation/__init__.py
csm_test_utils/rds_backup/generation/base.py
csm_test_utils/rds_backup/generation/cli.py
csm_test_utils/rds_backup/generation/pg2/__init__.py
csm_test_utils/rds_backup/generation/pg2/data.yaml
csm_test_utils/rds_backup/generation/pg2/db_methods.py
csm_test_utils/rds_backup/generation/sqla/__init__.py
csm_test_utils/rds_backup/generation/sqla/data.yaml
csm_test_utils/rds_backup/generation/sqla/db_methods.py
csm_test_utils/rds_backup/generation/sqla/db_model.py
csm_test_utils/rds_backup/generation/sqla/session.py
csm_test_utils-0.2.19.dist-info/LICENSE
csm_test_utils-0.2.19.dist-info/METADATA
csm_test_utils-0.2.19.dist-info/WHEEL
csm_test_utils-0.2.19.dist-info/pbr.json
csm_test_utils-0.2.19.dist-info/top_level.txt
csm_test_utils-0.2.19.dist-info/RECORD
