Metadata-Version: 2.1
Name: csm-test-utils
Version: 0.2.19
Summary: Utils for testing infrastructure created by customer service monitoring
Home-page: https://github.com/opentelekomcloud-infra/csm-test-utils
Author: OTC customer service monitoring team
Author-email: UNKNOWN
License: Apache-2.0
Platform: any
Classifier: Framework :: Flask
Classifier: Intended Audience :: Information Technology
Classifier: Programming Language :: Python :: 3
Classifier: Programming Language :: Python :: 3.7
Classifier: Programming Language :: Python :: 3.8
Classifier: Programming Language :: Python :: 3.9
Requires-Dist: ocomone (>=0.4.1)
Requires-Dist: requests (>=2.22)
Requires-Dist: influx-line-protocol (>=0.1.3)
Requires-Dist: wrapt (>=1.11)
Requires-Dist: PyYAML (<5.2,>=5.1.2)
Requires-Dist: botocore (>=1.13)
Requires-Dist: boto3 (>=1.10)
Requires-Dist: flask (<1.2,>=1.1)
Requires-Dist: psycopg2-binary
Requires-Dist: pyyml
Requires-Dist: SQLAlchemy
